{
  "$schema": "https://fundingschemas.blob.core.windows.net/schemas/logicalmodel-1.0.json#schema",
  "schemaVersion": "1.0",
  "funding": {
    "templateVersion": "1.0",
    "id": "GAG-AC-2021-Information-LocalAuthority-200-1_0",
    "fundingVersion": "1_0",
    "status": "Released",
    "fundingStream": {
      "code": "GAG",
      "name": "GAG"
    },
    "fundingPeriod": {
      "id": "AC-2022",
      "period": "2021",
      "name": "Financial Year 2020-21",
      "type": "AC",
      "startDate": "2019-08-01T00:00:00+01:00",
      "endDate": "2020-07-31T00:00:00+01:00"
    },
    "organisationGroup": {
      "groupTypeCode": "LocalAuthority",
      "groupTypeIdentifier": "LACode",
      "identifierValue": "200",
      "groupTypeClassification": "GeographicalBoundary",
      "name": "Local Authority 1",
      "searchableName": "LocalAuthority1",
      "identifiers": [
        {
          "type": "UKPRN",
          "value": "1000000"
        },
        {
          "type": "LACode",
          "value": "200"
        }
      ]
    },
    "fundingValue": {
      "totalValue": 24000.0,
      "fundingLines": [
        {
          "name": "Total GAG before deductions and recoupment",
          "fundingLineCode": "GAG-001",
          "value": 7680,
          "templateLineId": 2,
          "type": "Information",
          "distributionPeriods": [],
          "fundingLines": [
            {
              "name": "Schools Block before recoupment",
              "fundingLineCode": "GAG-003",
              "value": 1280,
              "templateLineId": 4,
              "type": "Information",
              "calculations": [],
              "distributionPeriods": [],
              "fundingLines": [
                {
                  "name": "Provisional Schools Block Funding Excluding Growth",
                  "fundingLineCode": "GAG-020",
                  "value": 0,
                  "templateLineId": 239,
                  "type": "Information",
                  "calculations": [
                    {
                      "name": "Provisional Schools Block Funding Excluding Growth",
                      "type": "Number",
                      "aggregationType": "Sum",
                      "formulaText": "",
                      "templateCalculationId": 241,
                      "value": 640.0,
                      "valueFormat": "Currency",
                      "calculations": []
                    }
                  ],
                  "distributionPeriods": [],
                  "fundingLines": [
                    {
                      "name": "Pupil Led Factors",
                      "fundingLineCode": "GAG-004",
                      "value": 1280,
                      "templateLineId": 5,
                      "type": "Information",
                      "calculations": [
                        {
                          "name": "Primary pupil sub-total",
                          "type": "Cash",
                          "aggregationType": "Sum",
                          "formulaText": "",
                          "templateCalculationId": 13,
                          "value": 640.0,
                          "valueFormat": "Currency",
                          "calculations": [
                            {
                              "name": "Primary Pupil Number",
                              "type": "PupilNumber",
                              "aggregationType": "Sum",
                              "formulaText": "",
                              "templateCalculationId": 15,
                              "value": 640.0,
                              "valueFormat": "Number",
                              "calculations": []
                            }
                          ]
                        },
                        {
                          "name": "Secondary pupil sub-total",
                          "type": "Cash",
                          "aggregationType": "Sum",
                          "formulaText": "",
                          "templateCalculationId": 14,
                          "value": 640.0,
                          "valueFormat": "Currency",
                          "calculations": [
                            {
                              "name": "Secondary Pupil Number",
                              "type": "PupilNumber",
                              "aggregationType": "Sum",
                              "formulaText": "",
                              "templateCalculationId": 17,
                              "value": 640.0,
                              "valueFormat": "Number",
                              "calculations": []
                            }
                          ]
                        }
                      ],
                      "distributionPeriods": [],
                      "fundingLines": []
                    },
                    {
                      "name": "Funding Through Premises and Mobility Factors",
                      "fundingLineCode": "GAG-007",
                      "value": 0,
                      "templateLineId": 6,
                      "type": "Information",
                      "calculations": [
                        {
                          "name": "Premises and Mobility Factors",
                          "type": "Cash",
                          "aggregationType": "Sum",
                          "formulaText": "",
                          "templateCalculationId": 19,
                          "value": 640.0,
                          "valueFormat": "Currency"
                        }
                      ],
                      "distributionPeriods": [],
                      "fundingLines": []
                    }
                  ]
                },
                {
                  "name": "LA Protection",
                  "fundingLineCode": "GAG-021",
                  "value": 0,
                  "templateLineId": 240,
                  "type": "Information",
                  "calculations": [
                    {
                      "name": "Current Year Local Authority Protection",
                      "type": "Cash",
                      "aggregationType": "Sum",
                      "formulaText": "",
                      "templateCalculationId": 243,
                      "value": 640.0,
                      "valueFormat": "Currency",
                      "calculations": [
                        {
                          "name": "Current Year Provisional Schools Block Excluding Growth Funding Per Pupil",
                          "type": "Rate",
                          "aggregationType": "None",
                          "formulaText": "",
                          "templateCalculationId": 246,
                          "value": 0.0,
                          "valueFormat": "Currency",
                          "calculations": [
                            {
                              "name": "Current Year School Block Pupil No",
                              "type": "PupilNumber",
                              "aggregationType": "Sum",
                              "formulaText": "",
                              "templateCalculationId": 242,
                              "value": 640.0,
                              "valueFormat": "Number",
                              "calculations": [
                                {
                                  "name": "Primary Pupil Number",
                                  "type": "PupilNumber",
                                  "aggregationType": "Sum",
                                  "formulaText": "",
                                  "templateCalculationId": 15,
                                  "value": 640.0,
                                  "valueFormat": "Number",
                                  "calculations": []
                                },
                                {
                                  "name": "Secondary Pupil Number",
                                  "type": "PupilNumber",
                                  "aggregationType": "Sum",
                                  "formulaText": "",
                                  "templateCalculationId": 17,
                                  "value": 640.0,
                                  "valueFormat": "Number",
                                  "calculations": []
                                }
                              ]
                            },
                            {
                              "name": "Current Year Provisional Schools Block Funding Excluding Growth - NON CASH",
                              "type": "Number",
                              "aggregationType": "Sum",
                              "formulaText": "",
                              "templateCalculationId": 248,
                              "value": 640.0,
                              "valueFormat": "Currency"
                            }
                          ]
                        },
                        {
                          "name": "Previous Year Schools Block Excluding Growth Funding Per Pupil",
                          "type": "Rate",
                          "aggregationType": "None",
                          "formulaText": "",
                          "templateCalculationId": 247,
                          "value": 0.0,
                          "valueFormat": "Currency",
                          "calculations": [
                            {
                              "name": "Previous Year Schools Block Pupil Numbers",
                              "type": "PupilNumber",
                              "aggregationType": "Sum",
                              "formulaText": "",
                              "templateCalculationId": 249,
                              "value": 640.0,
                              "valueFormat": "Number"
                            },
                            {
                              "name": "Previous Year Schools Block Excluding Growth Funding",
                              "type": "Number",
                              "aggregationType": "Sum",
                              "formulaText": "",
                              "templateCalculationId": 250,
                              "value": 640.0,
                              "valueFormat": "Currency"
                            }
                          ]
                        }
                      ]
                    },
                    {
                      "name": "Percentage Change between Current Year and Previous Year per Pupil Funding",
                      "type": "Number",
                      "aggregationType": "Average",
                      "formulaText": "",
                      "templateCalculationId": 244,
                      "value": 320.0,
                      "valueFormat": "Percentage",
                      "calculations": [
                        {
                          "name": "Current Year Provisional Schools Block Excluding Growth Funding Per Pupil",
                          "type": "Rate",
                          "aggregationType": "None",
                          "formulaText": "",
                          "templateCalculationId": 246,
                          "value": 0.0,
                          "valueFormat": "Currency",
                          "calculations": [
                            {
                              "name": "Current Year School Block Pupil No",
                              "type": "PupilNumber",
                              "aggregationType": "Sum",
                              "formulaText": "",
                              "templateCalculationId": 242,
                              "value": 640.0,
                              "valueFormat": "Number",
                              "calculations": [
                                {
                                  "name": "Primary Pupil Number",
                                  "type": "PupilNumber",
                                  "aggregationType": "Sum",
                                  "formulaText": "",
                                  "templateCalculationId": 15,
                                  "value": 640.0,
                                  "valueFormat": "Number",
                                  "calculations": []
                                },
                                {
                                  "name": "Secondary Pupil Number",
                                  "type": "PupilNumber",
                                  "aggregationType": "Sum",
                                  "formulaText": "",
                                  "templateCalculationId": 17,
                                  "value": 640.0,
                                  "valueFormat": "Number",
                                  "calculations": []
                                }
                              ]
                            },
                            {
                              "name": "Current Year Provisional Schools Block Funding Excluding Growth - NON CASH",
                              "type": "Number",
                              "aggregationType": "Sum",
                              "formulaText": "",
                              "templateCalculationId": 248,
                              "value": 640.0,
                              "valueFormat": "Currency"
                            }
                          ]
                        },
                        {
                          "name": "Previous Year Schools Block Excluding Growth Funding Per Pupil",
                          "type": "Rate",
                          "aggregationType": "None",
                          "formulaText": "",
                          "templateCalculationId": 247,
                          "value": 0.0,
                          "valueFormat": "Currency",
                          "calculations": [
                            {
                              "name": "Previous Year Schools Block Pupil Numbers",
                              "type": "PupilNumber",
                              "aggregationType": "Sum",
                              "formulaText": "",
                              "templateCalculationId": 249,
                              "value": 640.0,
                              "valueFormat": "Number"
                            },
                            {
                              "name": "Previous Year Schools Block Excluding Growth Funding",
                              "type": "Number",
                              "aggregationType": "Sum",
                              "formulaText": "",
                              "templateCalculationId": 250,
                              "value": 640.0,
                              "valueFormat": "Currency"
                            }
                          ]
                        }
                      ]
                    },
                    {
                      "name": "Percentage Change between Current Year and Previous Year per Pupil Funding after local authority protection",
                      "type": "Number",
                      "aggregationType": "Average",
                      "formulaText": "",
                      "templateCalculationId": 245,
                      "value": 320.0,
                      "valueFormat": "Percentage",
                      "calculations": [
                        {
                          "name": "Current Year Provisional Schools Block Excluding Growth Funding Per Pupil",
                          "type": "Rate",
                          "aggregationType": "None",
                          "formulaText": "",
                          "templateCalculationId": 246,
                          "value": 0.0,
                          "valueFormat": "Currency",
                          "calculations": [
                            {
                              "name": "Current Year School Block Pupil No",
                              "type": "PupilNumber",
                              "aggregationType": "Sum",
                              "formulaText": "",
                              "templateCalculationId": 242,
                              "value": 640.0,
                              "valueFormat": "Number",
                              "calculations": [
                                {
                                  "name": "Primary Pupil Number",
                                  "type": "PupilNumber",
                                  "aggregationType": "Sum",
                                  "formulaText": "",
                                  "templateCalculationId": 15,
                                  "value": 640.0,
                                  "valueFormat": "Number",
                                  "calculations": []
                                },
                                {
                                  "name": "Secondary Pupil Number",
                                  "type": "PupilNumber",
                                  "aggregationType": "Sum",
                                  "formulaText": "",
                                  "templateCalculationId": 17,
                                  "value": 640.0,
                                  "valueFormat": "Number",
                                  "calculations": []
                                }
                              ]
                            },
                            {
                              "name": "Current Year Provisional Schools Block Funding Excluding Growth - NON CASH",
                              "type": "Number",
                              "aggregationType": "Sum",
                              "formulaText": "",
                              "templateCalculationId": 248,
                              "value": 640.0,
                              "valueFormat": "Currency"
                            }
                          ]
                        },
                        {
                          "name": "Previous Year Schools Block Excluding Growth Funding Per Pupil",
                          "type": "Rate",
                          "aggregationType": "None",
                          "formulaText": "",
                          "templateCalculationId": 247,
                          "value": 0.0,
                          "valueFormat": "Currency",
                          "calculations": [
                            {
                              "name": "Previous Year Schools Block Pupil Numbers",
                              "type": "PupilNumber",
                              "aggregationType": "Sum",
                              "formulaText": "",
                              "templateCalculationId": 249,
                              "value": 640.0,
                              "valueFormat": "Number"
                            },
                            {
                              "name": "Previous Year Schools Block Excluding Growth Funding",
                              "type": "Number",
                              "aggregationType": "Sum",
                              "formulaText": "",
                              "templateCalculationId": 250,
                              "value": 640.0,
                              "valueFormat": "Currency"
                            }
                          ]
                        }
                      ]
                    }
                  ],
                  "distributionPeriods": [],
                  "fundingLines": []
                },
                {
                  "name": "Growth funding",
                  "fundingLineCode": "GAG-006",
                  "value": 0,
                  "templateLineId": 7,
                  "type": "Information",
                  "calculations": [
                    {
                      "name": "Growth",
                      "type": "Cash",
                      "aggregationType": "Sum",
                      "formulaText": "",
                      "templateCalculationId": 20,
                      "value": 640.0,
                      "valueFormat": "Currency"
                    }
                  ],
                  "distributionPeriods": [],
                  "fundingLines": []
                }
              ]
            },
            {
              "name": "Central School Services Block",
              "fundingLineCode": "GAG-008",
              "value": 640,
              "templateLineId": 8,
              "type": "Information",
              "calculations": [],
              "distributionPeriods": [],
              "fundingLines": [
                {
                  "name": "CSSB Pupil Led Funding",
                  "fundingLineCode": "GAG-012",
                  "value": 640,
                  "templateLineId": 23,
                  "type": "Information",
                  "calculations": [
                    {
                      "name": "CSSB Pupil Led Total",
                      "type": "Cash",
                      "aggregationType": "Sum",
                      "formulaText": "",
                      "templateCalculationId": 24,
                      "value": 640.0,
                      "valueFormat": "Currency",
                      "calculations": [
                        {
                          "name": "CSSB Pupil Number",
                          "type": "PupilNumber",
                          "aggregationType": "Sum",
                          "formulaText": "",
                          "templateCalculationId": 26,
                          "value": 640.0,
                          "valueFormat": "Number",
                          "calculations": []
                        }
                      ]
                    }
                  ],
                  "distributionPeriods": [],
                  "fundingLines": []
                },
                {
                  "name": "Funding for Historic Commitments",
                  "fundingLineCode": "GAG-013",
                  "value": 0,
                  "templateLineId": 27,
                  "type": "Information",
                  "calculations": [
                    {
                      "name": "Actual CSSB Funding for Historic Commitments",
                      "type": "Cash",
                      "aggregationType": "Sum",
                      "formulaText": "",
                      "templateCalculationId": 28,
                      "value": 640.0,
                      "valueFormat": "Currency"
                    }
                  ],
                  "distributionPeriods": [],
                  "fundingLines": []
                }
              ]
            },
            {
              "name": "Early Years Block",
              "fundingLineCode": "GAG-009",
              "value": 3200,
              "templateLineId": 9,
              "type": "Information",
              "distributionPeriods": [],
              "fundingLines": [
                {
                  "name": "Universal Entitlement for 3 and 4 Year Olds",
                  "fundingLineCode": "GAG-014",
                  "value": 640,
                  "templateLineId": 130,
                  "type": "Information",
                  "calculations": [
                    {
                      "name": "Universal Entitlement for 3 and 4 Year Olds total",
                      "type": "Cash",
                      "aggregationType": "Sum",
                      "formulaText": "",
                      "templateCalculationId": 131,
                      "value": 640.0,
                      "valueFormat": "Currency",
                      "calculations": [
                        {
                          "name": "Total 3 and 4 Year Olds (PTE)",
                          "type": "PupilNumber",
                          "aggregationType": "Average",
                          "formulaText": "",
                          "templateCalculationId": 133,
                          "value": 320.0,
                          "valueFormat": "Number"
                        }
                      ]
                    }
                  ],
                  "distributionPeriods": [],
                  "fundingLines": []
                },
                {
                  "name": "Funding for Additional Hours for working parents",
                  "fundingLineCode": "GAG-015",
                  "value": 640,
                  "templateLineId": 135,
                  "type": "Information",
                  "calculations": [
                    {
                      "name": "Funding for Additional Hours for working parents total",
                      "type": "Cash",
                      "aggregationType": "Sum",
                      "formulaText": "",
                      "templateCalculationId": 136,
                      "value": 640.0,
                      "valueFormat": "Currency",
                      "calculations": [
                        {
                          "name": "Total 3 and 4 Year Old for Additional Hours for Working Parents (PTE)",
                          "type": "PupilNumber",
                          "aggregationType": "Average",
                          "formulaText": "",
                          "templateCalculationId": 138,
                          "value": 320.0,
                          "valueFormat": "Number"
                        }
                      ]
                    }
                  ],
                  "distributionPeriods": [],
                  "fundingLines": []
                },
                {
                  "name": "Participation Funding for Disadvantaged 2 Year Olds",
                  "fundingLineCode": "GAG-016",
                  "value": 640,
                  "templateLineId": 140,
                  "type": "Information",
                  "calculations": [
                    {
                      "name": "Participation Funding for Disadvantaged 2 Year Olds total",
                      "type": "Cash",
                      "aggregationType": "Sum",
                      "formulaText": "",
                      "templateCalculationId": 141,
                      "value": 640.0,
                      "valueFormat": "Currency",
                      "calculations": [
                        {
                          "name": "Total 2 Year Olds (PTE)",
                          "type": "PupilNumber",
                          "aggregationType": "Sum",
                          "formulaText": "",
                          "templateCalculationId": 143,
                          "value": 640.0,
                          "valueFormat": "Number"
                        }
                      ]
                    }
                  ],
                  "distributionPeriods": [],
                  "fundingLines": []
                },
                {
                  "name": "Funding Allocation for Early Years Pupil Premium",
                  "fundingLineCode": "GAG-017",
                  "value": 640,
                  "templateLineId": 145,
                  "type": "Information",
                  "calculations": [
                    {
                      "name": "Funding Allocation for Early Years Pupil Premium total",
                      "type": "Cash",
                      "aggregationType": "Sum",
                      "formulaText": "",
                      "templateCalculationId": 146,
                      "value": 640.0,
                      "valueFormat": "Currency",
                      "calculations": [
                        {
                          "name": "Pupil Premium Pupil Count for 3 to 4 Year Olds (PTE)",
                          "type": "PupilNumber",
                          "aggregationType": "Sum",
                          "formulaText": "",
                          "templateCalculationId": 148,
                          "value": 640.0,
                          "valueFormat": "Number"
                        }
                      ]
                    }
                  ],
                  "distributionPeriods": [],
                  "fundingLines": []
                },
                {
                  "name": "Funding Allocation for Maintained Nursery Supplement",
                  "fundingLineCode": "GAG-018",
                  "value": 640,
                  "templateLineId": 150,
                  "type": "Information",
                  "calculations": [
                    {
                      "name": "Funding Allocation for Maintained Nursery Supplement total",
                      "type": "Cash",
                      "aggregationType": "Sum",
                      "formulaText": "",
                      "templateCalculationId": 151,
                      "value": 640.0,
                      "valueFormat": "Currency",
                      "calculations": [
                        {
                          "name": "Maintained Nursery Schools Supplement (PTE)",
                          "type": "PupilNumber",
                          "aggregationType": "Sum",
                          "formulaText": "",
                          "templateCalculationId": 153,
                          "value": 640.0,
                          "valueFormat": "Number"
                        }
                      ]
                    }
                  ],
                  "distributionPeriods": [],
                  "fundingLines": []
                },
                {
                  "name": "Funding Allocation for Disability Access Fund",
                  "fundingLineCode": "GAG-019",
                  "value": 0,
                  "templateLineId": 155,
                  "type": "Information",
                  "calculations": [
                    {
                      "name": "Disability Access Fund",
                      "type": "Cash",
                      "aggregationType": "Sum",
                      "formulaText": "",
                      "templateCalculationId": 238,
                      "value": 640.0,
                      "valueFormat": "Currency"
                    }
                  ],
                  "distributionPeriods": [],
                  "fundingLines": []
                }
              ]
            },
            {
              "name": "High Needs Block before deductions",
              "fundingLineCode": "GAG-010",
              "value": 2560,
              "templateLineId": 10,
              "type": "Information",
              "calculations": [
                {
                  "name": "HN Block Baseline",
                  "type": "Cash",
                  "aggregationType": "Sum",
                  "formulaText": "",
                  "templateCalculationId": 29,
                  "value": 640.0,
                  "valueFormat": "Currency"
                },
                {
                  "name": "Additional Funding For free Schools",
                  "type": "Cash",
                  "aggregationType": "Sum",
                  "formulaText": "",
                  "templateCalculationId": 237,
                  "value": 640.0,
                  "valueFormat": "Currency"
                },
                {
                  "name": "Basic Entitlement",
                  "type": "Cash",
                  "aggregationType": "Sum",
                  "formulaText": "",
                  "templateCalculationId": 30,
                  "value": 640.0,
                  "valueFormat": "Currency",
                  "calculations": [
                    {
                      "name": "Basic Entitlement Per Pupil Number",
                      "type": "PupilNumber",
                      "aggregationType": "Sum",
                      "formulaText": "",
                      "templateCalculationId": 32,
                      "value": 640.0,
                      "valueFormat": "Number"
                    }
                  ]
                },
                {
                  "name": "Import/Export Adjustment",
                  "type": "Cash",
                  "aggregationType": "Sum",
                  "formulaText": "",
                  "templateCalculationId": 33,
                  "value": 640.0,
                  "valueFormat": "Currency",
                  "calculations": [
                    {
                      "name": "Import/Export Adjustment per pupil number",
                      "type": "PupilNumber",
                      "aggregationType": "Sum",
                      "formulaText": "",
                      "templateCalculationId": 34,
                      "value": 640.0,
                      "valueFormat": "Number"
                    }
                  ]
                },
                {
                  "name": "Additional High Needs Funding",
                  "type": "Cash",
                  "aggregationType": "Average",
                  "formulaText": "",
                  "templateCalculationId": 36,
                  "value": 320.0,
                  "valueFormat": "Currency",
                  "calculations": [
                    {
                      "name": "Mid 2019 Age 2-18 ONS Population Projection",
                      "type": "PupilNumber",
                      "aggregationType": "Sum",
                      "formulaText": "",
                      "templateCalculationId": 37,
                      "value": 640.0,
                      "valueFormat": "Number"
                    }
                  ]
                }
              ],
              "distributionPeriods": [],
              "fundingLines": []
            }
          ]
        },
        {
          "name": "Total GAG after deductions and recoupment",
          "fundingLineCode": "GAG-002",
          "value": 30720,
          "templateLineId": 3,
          "type": "Payment",
          "calculations": [],
          "distributionPeriods": [
            {
              "value": 14000,
              "distributionPeriodId": "FY-1920",
              "profilePeriods": [
                {
                  "type": "CalendarMonth",
                  "typeValue": "October",
                  "year": 1920,
                  "occurrence": 1,
                  "profiledValue": 14000,
                  "distributionPeriodId": "FY-1920"
                }
              ]
            },
            {
              "value": 10000,
              "distributionPeriodId": "AC-2021",
              "profilePeriods": [
                {
                  "type": "CalendarMonth",
                  "typeValue": "April",
                  "year": 2021,
                  "occurrence": 1,
                  "profiledValue": 10000,
                  "distributionPeriodId": "AC-2021"
                }
              ]
            }
          ],
          "fundingLines": [
            {
              "name": "Central School Services Block",
              "fundingLineCode": "GAG-008",
              "value": 640,
              "templateLineId": 8,
              "type": "Information",
              "calculations": [],
              "distributionPeriods": [],
              "fundingLines": [
                {
                  "name": "CSSB Pupil Led Funding",
                  "fundingLineCode": "GAG-012",
                  "value": 640,
                  "templateLineId": 23,
                  "type": "Information",
                  "calculations": [
                    {
                      "name": "CSSB Pupil Led Total",
                      "type": "Cash",
                      "aggregationType": "Sum",
                      "formulaText": "",
                      "templateCalculationId": 24,
                      "value": 640.0,
                      "valueFormat": "Currency",
                      "calculations": [
                        {
                          "name": "CSSB Pupil Number",
                          "type": "PupilNumber",
                          "aggregationType": "Sum",
                          "formulaText": "",
                          "templateCalculationId": 26,
                          "value": 640.0,
                          "valueFormat": "Number",
                          "calculations": []
                        }
                      ]
                    }
                  ],
                  "distributionPeriods": [],
                  "fundingLines": []
                },
                {
                  "name": "Funding for Historic Commitments",
                  "fundingLineCode": "GAG-013",
                  "value": 0,
                  "templateLineId": 27,
                  "type": "Information",
                  "calculations": [
                    {
                      "name": "Actual CSSB Funding for Historic Commitments",
                      "type": "Cash",
                      "aggregationType": "Sum",
                      "formulaText": "",
                      "templateCalculationId": 28,
                      "value": 640.0,
                      "valueFormat": "Currency"
                    }
                  ],
                  "distributionPeriods": [],
                  "fundingLines": []
                }
              ]
            },
            {
              "name": "Early Years Block",
              "fundingLineCode": "GAG-009",
              "value": 3200,
              "templateLineId": 9,
              "type": "Information",
              "calculations": [],
              "distributionPeriods": [],
              "fundingLines": [
                {
                  "name": "Universal Entitlement for 3 and 4 Year Olds",
                  "fundingLineCode": "GAG-014",
                  "value": 640,
                  "templateLineId": 130,
                  "type": "Information",
                  "calculations": [
                    {
                      "name": "Universal Entitlement for 3 and 4 Year Olds total",
                      "type": "Cash",
                      "aggregationType": "Sum",
                      "formulaText": "",
                      "templateCalculationId": 131,
                      "value": 640.0,
                      "valueFormat": "Currency",
                      "calculations": [
                        {
                          "name": "Total 3 and 4 Year Olds (PTE)",
                          "type": "PupilNumber",
                          "aggregationType": "Average",
                          "formulaText": "",
                          "templateCalculationId": 133,
                          "value": 320.0,
                          "valueFormat": "Number"
                        }
                      ]
                    }
                  ],
                  "distributionPeriods": [],
                  "fundingLines": []
                },
                {
                  "name": "Funding for Additional Hours for working parents",
                  "fundingLineCode": "GAG-015",
                  "value": 640,
                  "templateLineId": 135,
                  "type": "Information",
                  "calculations": [
                    {
                      "name": "Funding for Additional Hours for working parents total",
                      "type": "Cash",
                      "aggregationType": "Sum",
                      "formulaText": "",
                      "templateCalculationId": 136,
                      "value": 640.0,
                      "valueFormat": "Currency",
                      "calculations": [
                        {
                          "name": "Total 3 and 4 Year Old for Additional Hours for Working Parents (PTE)",
                          "type": "PupilNumber",
                          "aggregationType": "Average",
                          "formulaText": "",
                          "templateCalculationId": 138,
                          "value": 320.0,
                          "valueFormat": "Number"
                        }
                      ]
                    }
                  ],
                  "distributionPeriods": [],
                  "fundingLines": []
                },
                {
                  "name": "Participation Funding for Disadvantaged 2 Year Olds",
                  "fundingLineCode": "GAG-016",
                  "value": 640,
                  "templateLineId": 140,
                  "type": "Information",
                  "calculations": [
                    {
                      "name": "Participation Funding for Disadvantaged 2 Year Olds total",
                      "type": "Cash",
                      "aggregationType": "Sum",
                      "formulaText": "",
                      "templateCalculationId": 141,
                      "value": 640.0,
                      "valueFormat": "Currency",
                      "calculations": [
                        {
                          "name": "Total 2 Year Olds (PTE)",
                          "type": "PupilNumber",
                          "aggregationType": "Sum",
                          "formulaText": "",
                          "templateCalculationId": 143,
                          "value": 640.0,
                          "valueFormat": "Number"
                        }
                      ]
                    }
                  ],
                  "distributionPeriods": [],
                  "fundingLines": []
                },
                {
                  "name": "Funding Allocation for Early Years Pupil Premium",
                  "fundingLineCode": "GAG-017",
                  "value": 640,
                  "templateLineId": 145,
                  "type": "Information",
                  "calculations": [
                    {
                      "name": "Funding Allocation for Early Years Pupil Premium total",
                      "type": "Cash",
                      "aggregationType": "Sum",
                      "formulaText": "",
                      "templateCalculationId": 146,
                      "value": 640.0,
                      "valueFormat": "Currency",
                      "calculations": [
                        {
                          "name": "Pupil Premium Pupil Count for 3 to 4 Year Olds (PTE)",
                          "type": "PupilNumber",
                          "aggregationType": "Sum",
                          "formulaText": "",
                          "templateCalculationId": 148,
                          "value": 640.0,
                          "valueFormat": "Number"
                        }
                      ]
                    }
                  ],
                  "distributionPeriods": [],
                  "fundingLines": []
                },
                {
                  "name": "Funding Allocation for Maintained Nursery Supplement",
                  "fundingLineCode": "GAG-018",
                  "value": 640,
                  "templateLineId": 150,
                  "type": "Information",
                  "calculations": [
                    {
                      "name": "Funding Allocation for Maintained Nursery Supplement total",
                      "type": "Cash",
                      "aggregationType": "Sum",
                      "formulaText": "",
                      "templateCalculationId": 151,
                      "value": 640.0,
                      "valueFormat": "Currency",
                      "calculations": [
                        {
                          "name": "Maintained Nursery Schools Supplement (PTE)",
                          "type": "PupilNumber",
                          "aggregationType": "Sum",
                          "formulaText": "",
                          "templateCalculationId": 153,
                          "value": 640.0,
                          "valueFormat": "Number"
                        }
                      ]
                    }
                  ],
                  "distributionPeriods": [],
                  "fundingLines": []
                },
                {
                  "name": "Funding Allocation for Disability Access Fund",
                  "fundingLineCode": "GAG-019",
                  "value": 0,
                  "templateLineId": 155,
                  "type": "Information",
                  "calculations": [
                    {
                      "name": "Disability Access Fund",
                      "type": "Cash",
                      "aggregationType": "Sum",
                      "formulaText": "",
                      "templateCalculationId": 238,
                      "value": 640.0,
                      "valueFormat": "Currency"
                    }
                  ],
                  "distributionPeriods": [],
                  "fundingLines": []
                }
              ]
            },
            {
              "name": "Total High Needs Block After Deductions",
              "fundingLineCode": "GAG-011",
              "value": 29440,
              "templateLineId": 11,
              "type": "Information",
              "calculations": [
                {
                  "name": "HN after deductions",
                  "type": "Cash",
                  "aggregationType": "Sum",
                  "formulaText": "",
                  "templateCalculationId": 39,
                  "value": 640.0,
                  "valueFormat": "Currency",
                  "calculations": [
                    {
                      "name": "HN Deductions",
                      "type": "Cash",
                      "aggregationType": "Sum",
                      "formulaText": "",
                      "templateCalculationId": 40,
                      "value": 640.0,
                      "valueFormat": "Currency",
                      "calculations": [
                        {
                          "name": "Mainstream Academies (SEN units and Resourced provision)",
                          "type": "Cash",
                          "aggregationType": "Sum",
                          "formulaText": "",
                          "templateCalculationId": 42,
                          "value": 640.0,
                          "valueFormat": "Currency",
                          "calculations": [
                            {
                              "name": "Mainstream Academies (SEN units and Resourced provision) Pre-16 SEN Places @6k",
                              "type": "Cash",
                              "aggregationType": "Sum",
                              "formulaText": "",
                              "templateCalculationId": 50,
                              "value": 640.0,
                              "valueFormat": "Currency",
                              "calculations": [
                                {
                                  "name": "Mainstream Academies (SEN units and Resourced provision) Pre-16 SEN Places @6k SEN places deduction",
                                  "type": "Cash",
                                  "aggregationType": "Sum",
                                  "formulaText": "",
                                  "templateCalculationId": 64,
                                  "value": 640.0,
                                  "valueFormat": "Currency",
                                  "calculations": [
                                    {
                                      "name": "Mainstream Academies (SEN units and Resourced provision) Pre-16 SEN Places @6k SEN places deduction April (Year 1) - August (Year 1)",
                                      "type": "PupilNumber",
                                      "aggregationType": "Sum",
                                      "formulaText": "",
                                      "templateCalculationId": 65,
                                      "value": 640.0,
                                      "valueFormat": "Number"
                                    },
                                    {
                                      "name": "Mainstream Academies (SEN units and Resourced provision) Pre-16 SEN Places @6k SEN places deduction September (Year 1) - March (Year 2)",
                                      "type": "PupilNumber",
                                      "aggregationType": "Sum",
                                      "formulaText": "",
                                      "templateCalculationId": 66,
                                      "value": 640.0,
                                      "valueFormat": "Number"
                                    }
                                  ]
                                }
                              ]
                            },
                            {
                              "name": "Mainstream Academies (SEN units and Resourced provision) Pre-16 SEN Places @10k",
                              "type": "Cash",
                              "aggregationType": "Sum",
                              "formulaText": "",
                              "templateCalculationId": 51,
                              "value": 640.0,
                              "valueFormat": "Currency",
                              "calculations": [
                                {
                                  "name": "Mainstream Academies (SEN units and Resourced provision) Pre-16 SEN Places @10k SEN places deduction",
                                  "type": "Cash",
                                  "aggregationType": "Sum",
                                  "formulaText": "",
                                  "templateCalculationId": 69,
                                  "value": 640.0,
                                  "valueFormat": "Currency",
                                  "calculations": [
                                    {
                                      "name": "Mainstream Academies (SEN units and Resourced provision) Pre-16 SEN Places @10k SEN places deduction April (Year 1) - August (Year 1)",
                                      "type": "PupilNumber",
                                      "aggregationType": "Sum",
                                      "formulaText": "",
                                      "templateCalculationId": 70,
                                      "value": 640.0,
                                      "valueFormat": "Number"
                                    },
                                    {
                                      "name": "Mainstream Academies (SEN units and Resourced provision) Pre-16 SEN Places @10k SEN places deduction September (Year 1) - March (Year 2)",
                                      "type": "PupilNumber",
                                      "aggregationType": "Sum",
                                      "formulaText": "",
                                      "templateCalculationId": 71,
                                      "value": 640.0,
                                      "valueFormat": "Number"
                                    }
                                  ]
                                }
                              ]
                            },
                            {
                              "name": "Post-16 SEN Places Main Stream Academies",
                              "type": "Cash",
                              "aggregationType": "Sum",
                              "formulaText": "",
                              "templateCalculationId": 52,
                              "value": 640.0,
                              "valueFormat": "Currency",
                              "calculations": [
                                {
                                  "name": "Mainstream Academies (SEN units and Resourced provision) Post-16 SEN Places Deduction",
                                  "type": "Cash",
                                  "aggregationType": "Sum",
                                  "formulaText": "",
                                  "templateCalculationId": 74,
                                  "value": 640.0,
                                  "valueFormat": "Currency",
                                  "calculations": [
                                    {
                                      "name": "Mainstream Academies (SEN units and Resourced provision) Post-16 SEN Places Deduction April (Year 1) - July (Year 1)",
                                      "type": "PupilNumber",
                                      "aggregationType": "Sum",
                                      "formulaText": "",
                                      "templateCalculationId": 75,
                                      "value": 640.0,
                                      "valueFormat": "Number"
                                    },
                                    {
                                      "name": "Mainstream Academies (SEN units and Resourced provision) Post-16 SEN Places Deduction August (Year 1) - March (Year 2)",
                                      "type": "PupilNumber",
                                      "aggregationType": "Sum",
                                      "formulaText": "",
                                      "templateCalculationId": 76,
                                      "value": 640.0,
                                      "valueFormat": "Number"
                                    }
                                  ]
                                }
                              ]
                            },
                            {
                              "name": "Mainstream Academies (SEN units and Resourced provision) Pre-16 AP Places",
                              "type": "Cash",
                              "aggregationType": "Sum",
                              "formulaText": "",
                              "templateCalculationId": 53,
                              "value": 640.0,
                              "valueFormat": "Currency",
                              "calculations": [
                                {
                                  "name": "Mainstream Academies (SEN units and Resourced provision) Pre-16 AP Places Deduction",
                                  "type": "Cash",
                                  "aggregationType": "Sum",
                                  "formulaText": "",
                                  "templateCalculationId": 79,
                                  "value": 640.0,
                                  "valueFormat": "Currency",
                                  "calculations": [
                                    {
                                      "name": "Mainstream Academies (SEN units and Resourced provision) Pre-16 AP Places Deduction April (Year 1) - August (Year 1)",
                                      "type": "PupilNumber",
                                      "aggregationType": "Sum",
                                      "formulaText": "",
                                      "templateCalculationId": 80,
                                      "value": 640.0,
                                      "valueFormat": "Number"
                                    },
                                    {
                                      "name": "Mainstream Academies (SEN units and Resourced provision) Pre-16 AP Places Deduction September (Year 1) - March (Year 2)",
                                      "type": "PupilNumber",
                                      "aggregationType": "Sum",
                                      "formulaText": "",
                                      "templateCalculationId": 81,
                                      "value": 640.0,
                                      "valueFormat": "Number"
                                    }
                                  ]
                                }
                              ]
                            }
                          ]
                        },
                        {
                          "name": "Special Academies",
                          "type": "Cash",
                          "aggregationType": "Sum",
                          "formulaText": "",
                          "templateCalculationId": 156,
                          "value": 640.0,
                          "valueFormat": "Currency",
                          "calculations": [
                            {
                              "name": "Special Academies Pre-16 SEN Places",
                              "type": "Cash",
                              "aggregationType": "Sum",
                              "formulaText": "",
                              "templateCalculationId": 158,
                              "value": 640.0,
                              "valueFormat": "Currency",
                              "calculations": [
                                {
                                  "name": "Special Academies Deduction",
                                  "type": "Cash",
                                  "aggregationType": "Sum",
                                  "formulaText": "",
                                  "templateCalculationId": 162,
                                  "value": 640.0,
                                  "valueFormat": "Currency",
                                  "calculations": [
                                    {
                                      "name": "Special Academies Pre-16 SEN Places Deduction April (Year 1) - July (Year 1)",
                                      "type": "PupilNumber",
                                      "aggregationType": "Sum",
                                      "formulaText": "",
                                      "templateCalculationId": 163,
                                      "value": 640.0,
                                      "valueFormat": "Number"
                                    },
                                    {
                                      "name": "Special Academies Pre-16 SEN Places Deduction August (Year 1) - March (Year 2)",
                                      "type": "PupilNumber",
                                      "aggregationType": "Sum",
                                      "formulaText": "",
                                      "templateCalculationId": 164,
                                      "value": 640.0,
                                      "valueFormat": "Number"
                                    }
                                  ]
                                }
                              ]
                            },
                            {
                              "name": "Special Academies Post-16 SEN Places",
                              "type": "Cash",
                              "aggregationType": "Sum",
                              "formulaText": "",
                              "templateCalculationId": 175,
                              "value": 640.0,
                              "valueFormat": "Currency",
                              "calculations": [
                                {
                                  "name": "Special Academies Post-16 SEN Places Deduction",
                                  "type": "Cash",
                                  "aggregationType": "Sum",
                                  "formulaText": "",
                                  "templateCalculationId": 89,
                                  "value": 640.0,
                                  "valueFormat": "Currency",
                                  "calculations": [
                                    {
                                      "name": "Special Academies Post-16 SEN Places Deduction April (Year 1) - July (Year 1)",
                                      "type": "PupilNumber",
                                      "aggregationType": "Sum",
                                      "formulaText": "",
                                      "templateCalculationId": 90,
                                      "value": 640.0,
                                      "valueFormat": "Number"
                                    },
                                    {
                                      "name": "Special Academies Post-16 SEN Places Deduction August (Year 1) - March (Year 2)",
                                      "type": "PupilNumber",
                                      "aggregationType": "Sum",
                                      "formulaText": "",
                                      "templateCalculationId": 91,
                                      "value": 640.0,
                                      "valueFormat": "Number"
                                    }
                                  ]
                                }
                              ]
                            },
                            {
                              "name": "Special Academies Pre-16 AP Places",
                              "type": "Cash",
                              "aggregationType": "Sum",
                              "formulaText": "",
                              "templateCalculationId": 174,
                              "value": 640.0,
                              "valueFormat": "Currency",
                              "calculations": [
                                {
                                  "name": "Special Academies Pre-16 AP Places Deduction",
                                  "type": "Cash",
                                  "aggregationType": "Sum",
                                  "formulaText": "",
                                  "templateCalculationId": 94,
                                  "value": 640.0,
                                  "valueFormat": "Currency",
                                  "calculations": [
                                    {
                                      "name": "Special Academies Pre-16 AP Places Deduction April (Year 1) - July (Year 1)",
                                      "type": "PupilNumber",
                                      "aggregationType": "Sum",
                                      "formulaText": "",
                                      "templateCalculationId": 95,
                                      "value": 640.0,
                                      "valueFormat": "Number"
                                    },
                                    {
                                      "name": "Special Academies Pre-16 AP Places Deduction August (Year 1) - March (Year 2)",
                                      "type": "PupilNumber",
                                      "aggregationType": "Sum",
                                      "formulaText": "",
                                      "templateCalculationId": 96,
                                      "value": 640.0,
                                      "valueFormat": "Number"
                                    }
                                  ]
                                }
                              ]
                            }
                          ]
                        },
                        {
                          "name": "Special Free Schools",
                          "type": "Cash",
                          "aggregationType": "Sum",
                          "formulaText": "",
                          "templateCalculationId": 157,
                          "value": 640.0,
                          "valueFormat": "Currency",
                          "calculations": [
                            {
                              "name": "Special Free Schools Pre-16 SEN Places",
                              "type": "Cash",
                              "aggregationType": "Sum",
                              "formulaText": "",
                              "templateCalculationId": 159,
                              "value": 640.0,
                              "valueFormat": "Currency",
                              "calculations": [
                                {
                                  "name": "Special Free Schools Deduction",
                                  "type": "Cash",
                                  "aggregationType": "Sum",
                                  "formulaText": "",
                                  "templateCalculationId": 167,
                                  "value": 640.0,
                                  "valueFormat": "Currency",
                                  "calculations": [
                                    {
                                      "name": "Special Free Schools Pre-16 SEN Places Deduction April (Year 1) - August (Year 1)",
                                      "type": "PupilNumber",
                                      "aggregationType": "Sum",
                                      "formulaText": "",
                                      "templateCalculationId": 168,
                                      "value": 640.0,
                                      "valueFormat": "Number"
                                    },
                                    {
                                      "name": "Special Free Schools Pre-16 SEN Places Deduction August (Year 1) - March (Year 2)",
                                      "type": "PupilNumber",
                                      "aggregationType": "Sum",
                                      "formulaText": "",
                                      "templateCalculationId": 169,
                                      "value": 640.0,
                                      "valueFormat": "Number"
                                    }
                                  ]
                                }
                              ]
                            },
                            {
                              "name": "Special Free Schools Post-16 SEN Places",
                              "type": "Cash",
                              "aggregationType": "Sum",
                              "formulaText": "",
                              "templateCalculationId": 161,
                              "value": 640.0,
                              "valueFormat": "Currency",
                              "calculations": [
                                {
                                  "name": "Special Free Schools Post-16 SEN Places Deduction",
                                  "type": "Cash",
                                  "aggregationType": "Sum",
                                  "formulaText": "",
                                  "templateCalculationId": 232,
                                  "value": 640.0,
                                  "valueFormat": "Currency",
                                  "calculations": [
                                    {
                                      "name": "Special Free Schools Post-16 SEN Places Deduction April (Year 1) - July (Year 1)",
                                      "type": "PupilNumber",
                                      "aggregationType": "Sum",
                                      "formulaText": "",
                                      "templateCalculationId": 176,
                                      "value": 640.0,
                                      "valueFormat": "Number"
                                    },
                                    {
                                      "name": "Special Free Schools Post-16 SEN Places Deduction August (Year 1) - March (Year 2)",
                                      "type": "PupilNumber",
                                      "aggregationType": "Sum",
                                      "formulaText": "",
                                      "templateCalculationId": 177,
                                      "value": 640.0,
                                      "valueFormat": "Number"
                                    }
                                  ]
                                }
                              ]
                            },
                            {
                              "name": "Special Free Schools Pre-16 AP Places",
                              "type": "Cash",
                              "aggregationType": "Sum",
                              "formulaText": "",
                              "templateCalculationId": 233,
                              "value": 640.0,
                              "valueFormat": "Currency",
                              "calculations": [
                                {
                                  "name": "Special Free Schools Pre-16 AP Places Deduction",
                                  "type": "Cash",
                                  "aggregationType": "Sum",
                                  "formulaText": "",
                                  "templateCalculationId": 234,
                                  "value": 640.0,
                                  "valueFormat": "Currency",
                                  "calculations": [
                                    {
                                      "name": "Special Free Schools Pre-16 AP Places Deduction April (Year 1) - August (Year 1)",
                                      "type": "PupilNumber",
                                      "aggregationType": "Sum",
                                      "formulaText": "",
                                      "templateCalculationId": 182,
                                      "value": 640.0,
                                      "valueFormat": "Number"
                                    },
                                    {
                                      "name": "Special Free Schools Pre-16 AP Places Deduction September (Year 1) - March (Year 2)",
                                      "type": "PupilNumber",
                                      "aggregationType": "Sum",
                                      "formulaText": "",
                                      "templateCalculationId": 183,
                                      "value": 640.0,
                                      "valueFormat": "Number"
                                    }
                                  ]
                                }
                              ]
                            }
                          ]
                        },
                        {
                          "name": "AP Academies & Free schools",
                          "type": "Cash",
                          "aggregationType": "Sum",
                          "formulaText": "",
                          "templateCalculationId": 184,
                          "value": 640.0,
                          "valueFormat": "Currency",
                          "calculations": [
                            {
                              "name": "AP Academies & Free schools Pre- 16 SEN places",
                              "type": "Cash",
                              "aggregationType": "Sum",
                              "formulaText": "",
                              "templateCalculationId": 185,
                              "value": 640.0,
                              "valueFormat": "Currency",
                              "calculations": [
                                {
                                  "name": "AP Academies and Free Schools Pre-16 SEN Places Deduction",
                                  "type": "Cash",
                                  "aggregationType": "Sum",
                                  "formulaText": "",
                                  "templateCalculationId": 186,
                                  "value": 640.0,
                                  "valueFormat": "Currency",
                                  "calculations": [
                                    {
                                      "name": "AP Academies and Free Schools Pre-16 SEN Places April (Year 1) - August (Year 1)",
                                      "type": "PupilNumber",
                                      "aggregationType": "Sum",
                                      "formulaText": "",
                                      "templateCalculationId": 189,
                                      "value": 640.0,
                                      "valueFormat": "Number"
                                    },
                                    {
                                      "name": "AP Academies and Free Schools Pre-16 SEN Places Sept (Year 1) - March (Year 2)",
                                      "type": "PupilNumber",
                                      "aggregationType": "Sum",
                                      "formulaText": "",
                                      "templateCalculationId": 190,
                                      "value": 640.0,
                                      "valueFormat": "Number"
                                    }
                                  ]
                                }
                              ]
                            },
                            {
                              "name": "AP Academies & Free schools Pre-16 AP Places",
                              "type": "Cash",
                              "aggregationType": "Sum",
                              "formulaText": "",
                              "templateCalculationId": 191,
                              "value": 640.0,
                              "valueFormat": "Currency",
                              "calculations": [
                                {
                                  "name": "AP Academies & Free schools Pre-16 AP Places Deduction",
                                  "type": "Cash",
                                  "aggregationType": "Sum",
                                  "formulaText": "",
                                  "templateCalculationId": 192,
                                  "value": 640.0,
                                  "valueFormat": "Currency",
                                  "calculations": [
                                    {
                                      "name": "AP Academies & Free schools Pre-16 AP Places Deduction April (Year 1) - August (Year 1)",
                                      "type": "PupilNumber",
                                      "aggregationType": "Sum",
                                      "formulaText": "",
                                      "templateCalculationId": 195,
                                      "value": 640.0,
                                      "valueFormat": "Number"
                                    },
                                    {
                                      "name": "AP Academies & Free schools Pre-16 AP Places Deduction September (Year 1) - March (Year 2)",
                                      "type": "PupilNumber",
                                      "aggregationType": "Sum",
                                      "formulaText": "",
                                      "templateCalculationId": 196,
                                      "value": 640.0,
                                      "valueFormat": "Number"
                                    }
                                  ]
                                }
                              ]
                            }
                          ]
                        },
                        {
                          "name": "Maintained Special Schools",
                          "type": "Cash",
                          "aggregationType": "Sum",
                          "formulaText": "",
                          "templateCalculationId": 197,
                          "value": 640.0,
                          "valueFormat": "Currency",
                          "calculations": [
                            {
                              "name": "Maintained Special Schools Post-16 SEN Places",
                              "type": "Cash",
                              "aggregationType": "Sum",
                              "formulaText": "",
                              "templateCalculationId": 198,
                              "value": 640.0,
                              "valueFormat": "Currency",
                              "calculations": [
                                {
                                  "name": "Maintained Special Schools Post-16 SEN Places deduction",
                                  "type": "Cash",
                                  "aggregationType": "Sum",
                                  "formulaText": "",
                                  "templateCalculationId": 199,
                                  "value": 640.0,
                                  "valueFormat": "Currency",
                                  "calculations": [
                                    {
                                      "name": "Maintained Special Schools Post-16 SEN Places Deduction April (Year 1) - July (Year 1)",
                                      "type": "PupilNumber",
                                      "aggregationType": "Sum",
                                      "formulaText": "",
                                      "templateCalculationId": 202,
                                      "value": 640.0,
                                      "valueFormat": "Number"
                                    },
                                    {
                                      "name": "Maintained Special Schools Post-16 SEN Places Deduction August (Year 1) - March (Year 2)",
                                      "type": "PupilNumber",
                                      "aggregationType": "Sum",
                                      "formulaText": "",
                                      "templateCalculationId": 203,
                                      "value": 640.0,
                                      "valueFormat": "Number"
                                    }
                                  ]
                                }
                              ]
                            }
                          ]
                        },
                        {
                          "name": "Maintained Mainstream Schools",
                          "type": "Cash",
                          "aggregationType": "Sum",
                          "formulaText": "",
                          "templateCalculationId": 204,
                          "value": 640.0,
                          "valueFormat": "Currency",
                          "calculations": [
                            {
                              "name": "Maintained Mainstream Schools Post-16 SEN Places",
                              "type": "Cash",
                              "aggregationType": "Sum",
                              "formulaText": "",
                              "templateCalculationId": 205,
                              "value": 640.0,
                              "valueFormat": "Currency",
                              "calculations": [
                                {
                                  "name": "Maintained Mainstream Schools Post-16 SEN Places Deduction",
                                  "type": "Cash",
                                  "aggregationType": "Sum",
                                  "formulaText": "",
                                  "templateCalculationId": 206,
                                  "value": 640.0,
                                  "valueFormat": "Currency",
                                  "calculations": [
                                    {
                                      "name": "Maintained Mainstream Schools Post-16 SEN Places Deduction April (Year 1) - July (Year 1)",
                                      "type": "PupilNumber",
                                      "aggregationType": "Sum",
                                      "formulaText": "",
                                      "templateCalculationId": 209,
                                      "value": 640.0,
                                      "valueFormat": "Number"
                                    },
                                    {
                                      "name": "Maintained Mainstream Schools Post-16 SEN Places Deduction August (Year 1) - March (Year 2)",
                                      "type": "PupilNumber",
                                      "aggregationType": "Sum",
                                      "formulaText": "",
                                      "templateCalculationId": 210,
                                      "value": 640.0,
                                      "valueFormat": "Number"
                                    }
                                  ]
                                }
                              ]
                            }
                          ]
                        },
                        {
                          "name": "Hospital Academies",
                          "type": "Cash",
                          "aggregationType": "Sum",
                          "formulaText": "",
                          "templateCalculationId": 211,
                          "value": 640.0,
                          "valueFormat": "Currency",
                          "calculations": [
                            {
                              "name": "Hospital Academies Funding Total Hospital Education",
                              "type": "Cash",
                              "aggregationType": "Sum",
                              "formulaText": "",
                              "templateCalculationId": 212,
                              "value": 640.0,
                              "valueFormat": "Currency",
                              "calculations": [
                                {
                                  "name": "Hospital Academies Funding Total Hospital Education Deduction",
                                  "type": "Cash",
                                  "aggregationType": "Sum",
                                  "formulaText": "",
                                  "templateCalculationId": 213,
                                  "value": 640.0,
                                  "valueFormat": "Currency",
                                  "calculations": [
                                    {
                                      "name": "Hospital Academies Funding Total Hospital Education Deduction April (Year 1) - August (Year 1)",
                                      "type": "PupilNumber",
                                      "aggregationType": "Sum",
                                      "formulaText": "",
                                      "templateCalculationId": 214,
                                      "value": 640.0,
                                      "valueFormat": "Number"
                                    },
                                    {
                                      "name": "Hospital Academies Funding Total Hospital Education Deduction September (Year 1) - March (Year 2)",
                                      "type": "PupilNumber",
                                      "aggregationType": "Sum",
                                      "formulaText": "",
                                      "templateCalculationId": 215,
                                      "value": 640.0,
                                      "valueFormat": "Number"
                                    }
                                  ]
                                }
                              ]
                            }
                          ]
                        },
                        {
                          "name": "16-19 Academies and Free Schools",
                          "type": "Cash",
                          "aggregationType": "Sum",
                          "formulaText": "",
                          "templateCalculationId": 218,
                          "value": 640.0,
                          "valueFormat": "Currency",
                          "calculations": [
                            {
                              "name": "16-19 Academies and Free Schools Total Post-16 Schools SEN Places",
                              "type": "Cash",
                              "aggregationType": "Sum",
                              "formulaText": "",
                              "templateCalculationId": 219,
                              "value": 640.0,
                              "valueFormat": "Currency",
                              "calculations": [
                                {
                                  "name": "16-19 Academies and Free Schools Total Post-16 Schools SEN Places Deduction",
                                  "type": "Cash",
                                  "aggregationType": "Sum",
                                  "formulaText": "",
                                  "templateCalculationId": 220,
                                  "value": 640.0,
                                  "valueFormat": "Currency",
                                  "calculations": [
                                    {
                                      "name": "16-19 Academies and Free Schools Total Post-16 Schools SEN Places Deduction April (Year 1) to July (Year 1)",
                                      "type": "PupilNumber",
                                      "aggregationType": "Sum",
                                      "formulaText": "",
                                      "templateCalculationId": 223,
                                      "value": 640.0,
                                      "valueFormat": "Number"
                                    },
                                    {
                                      "name": "16-19 Academies and Free Schools Total Post-16 Schools SEN Places Deduction August (Year 1) to March (Year 2)",
                                      "type": "PupilNumber",
                                      "aggregationType": "Sum",
                                      "formulaText": "",
                                      "templateCalculationId": 224,
                                      "value": 640.0,
                                      "valueFormat": "Number"
                                    }
                                  ]
                                }
                              ]
                            }
                          ]
                        },
                        {
                          "name": "FE and ILP",
                          "type": "Cash",
                          "aggregationType": "Sum",
                          "formulaText": "",
                          "templateCalculationId": 225,
                          "value": 640.0,
                          "valueFormat": "Currency",
                          "calculations": [
                            {
                              "name": "FE and ILP Places",
                              "type": "Cash",
                              "aggregationType": "Sum",
                              "formulaText": "",
                              "templateCalculationId": 226,
                              "value": 640.0,
                              "valueFormat": "Currency",
                              "calculations": [
                                {
                                  "name": "FE and ILP Deduction",
                                  "type": "Cash",
                                  "aggregationType": "Sum",
                                  "formulaText": "",
                                  "templateCalculationId": 227,
                                  "value": 640.0,
                                  "valueFormat": "Currency",
                                  "calculations": [
                                    {
                                      "name": "FE and ILP Places April (Year 1) - July (Year 1)",
                                      "type": "PupilNumber",
                                      "aggregationType": "Sum",
                                      "formulaText": "",
                                      "templateCalculationId": 128,
                                      "value": 640.0,
                                      "valueFormat": "Number"
                                    },
                                    {
                                      "name": "FE and ILP Places August (Year 1)- March (Year 2)",
                                      "type": "PupilNumber",
                                      "aggregationType": "Sum",
                                      "formulaText": "",
                                      "templateCalculationId": 129,
                                      "value": 640.0,
                                      "valueFormat": "Number"
                                    }
                                  ]
                                }
                              ]
                            }
                          ]
                        }
                      ]
                    },
                    {
                      "name": "HN before deductions",
                      "type": "Cash",
                      "aggregationType": "Sum",
                      "formulaText": "",
                      "templateCalculationId": 41,
                      "value": 640.0,
                      "valueFormat": "Currency"
                    }
                  ]
                }
              ],
              "distributionPeriods": [],
              "fundingLines": []
            },
            {
              "name": "School Block After recoupment",
              "fundingLineCode": "GAG-005",
              "value": 1280,
              "templateLineId": 12,
              "type": "Information",
              "calculations": [
                {
                  "name": "School Block After Recoupment",
                  "type": "Cash",
                  "aggregationType": "Sum",
                  "formulaText": "",
                  "templateCalculationId": 22,
                  "value": 640.0,
                  "valueFormat": "Currency",
                  "calculations": [
                    {
                      "name": "Recoupment",
                      "type": "Cash",
                      "aggregationType": "Sum",
                      "formulaText": "",
                      "templateCalculationId": 21,
                      "value": 640.0,
                      "valueFormat": "Currency",
                      "calculations": []
                    }
                  ]
                }
              ],
              "distributionPeriods": [],
              "fundingLines": []
            }
          ]
        }
      ]
    },
    "providerFundings": [ "GAG-AC-2021-1000002-1_0", "GAG-AC-2021-1000000-1_0" ],
    "groupingReason": "Information",
    "statusChangedDate": "2019-12-05T09:22:49.9702997+00:00",
    "externalPublicationDate": "2019-09-27T23:00:00Z",
    "earliestPaymentAvailableDate": "2019-09-28T23:00:00Z"
  }
}